{"diffoscope-json-version": 1, "source1": "first/Processor$Type.class", "source2": "second/Processor$Type.class", "unified_diff": null, "details": [{"source1": "javap -verbose -constants -s -l -private {}", "source2": "javap -verbose -constants -s -l -private {}", "unified_diff": "@@ -1,33 +1,33 @@\n-  SHA-256 checksum 841cbf5b9b663137226a127ec8b69457a1824fce54e1652db6bad5c81cdce750\n+  SHA-256 checksum 7245a799c1cd347e84c5fa22462343d9baca3ff1dd80f81ba28c3c2141649251\n   Compiled from \"Processor.java\"\n public final class org.apache.commons.lang3.arch.Processor$Type extends java.lang.Enum<org.apache.commons.lang3.arch.Processor$Type>\n   minor version: 0\n   major version: 52\n   flags: (0x4031) ACC_PUBLIC, ACC_FINAL, ACC_SUPER, ACC_ENUM\n   this_class: #4                          // org/apache/commons/lang3/arch/Processor$Type\n   super_class: #16                        // java/lang/Enum\n   interfaces: 0, fields: 5, methods: 4, attributes: 3\n Constant pool:\n-   #1 = Fieldref           #4.#44         // org/apache/commons/lang3/arch/Processor$Type.$VALUES:[Lorg/apache/commons/lang3/arch/Processor$Type;\n-   #2 = Methodref          #45.#46        // \"[Lorg/apache/commons/lang3/arch/Processor$Type;\".clone:()Ljava/lang/Object;\n+   #1 = Fieldref           #4.#40         // org/apache/commons/lang3/arch/Processor$Type.$VALUES:[Lorg/apache/commons/lang3/arch/Processor$Type;\n+   #2 = Methodref          #41.#42        // \"[Lorg/apache/commons/lang3/arch/Processor$Type;\".clone:()Ljava/lang/Object;\n    #3 = Class              #25            // \"[Lorg/apache/commons/lang3/arch/Processor$Type;\"\n-   #4 = Class              #48            // org/apache/commons/lang3/arch/Processor$Type\n-   #5 = Methodref          #16.#49        // java/lang/Enum.valueOf:(Ljava/lang/Class;Ljava/lang/String;)Ljava/lang/Enum;\n-   #6 = Methodref          #16.#50        // java/lang/Enum.\"<init>\":(Ljava/lang/String;I)V\n+   #4 = Class              #44            // org/apache/commons/lang3/arch/Processor$Type\n+   #5 = Methodref          #16.#45        // java/lang/Enum.valueOf:(Ljava/lang/Class;Ljava/lang/String;)Ljava/lang/Enum;\n+   #6 = Methodref          #16.#46        // java/lang/Enum.\"<init>\":(Ljava/lang/String;I)V\n    #7 = String             #17            // X86\n-   #8 = Methodref          #4.#50         // org/apache/commons/lang3/arch/Processor$Type.\"<init>\":(Ljava/lang/String;I)V\n-   #9 = Fieldref           #4.#51         // org/apache/commons/lang3/arch/Processor$Type.X86:Lorg/apache/commons/lang3/arch/Processor$Type;\n+   #8 = Methodref          #4.#46         // org/apache/commons/lang3/arch/Processor$Type.\"<init>\":(Ljava/lang/String;I)V\n+   #9 = Fieldref           #4.#47         // org/apache/commons/lang3/arch/Processor$Type.X86:Lorg/apache/commons/lang3/arch/Processor$Type;\n   #10 = String             #21            // IA_64\n-  #11 = Fieldref           #4.#52         // org/apache/commons/lang3/arch/Processor$Type.IA_64:Lorg/apache/commons/lang3/arch/Processor$Type;\n+  #11 = Fieldref           #4.#48         // org/apache/commons/lang3/arch/Processor$Type.IA_64:Lorg/apache/commons/lang3/arch/Processor$Type;\n   #12 = String             #22            // PPC\n-  #13 = Fieldref           #4.#53         // org/apache/commons/lang3/arch/Processor$Type.PPC:Lorg/apache/commons/lang3/arch/Processor$Type;\n+  #13 = Fieldref           #4.#49         // org/apache/commons/lang3/arch/Processor$Type.PPC:Lorg/apache/commons/lang3/arch/Processor$Type;\n   #14 = String             #23            // UNKNOWN\n-  #15 = Fieldref           #4.#54         // org/apache/commons/lang3/arch/Processor$Type.UNKNOWN:Lorg/apache/commons/lang3/arch/Processor$Type;\n-  #16 = Class              #55            // java/lang/Enum\n+  #15 = Fieldref           #4.#50         // org/apache/commons/lang3/arch/Processor$Type.UNKNOWN:Lorg/apache/commons/lang3/arch/Processor$Type;\n+  #16 = Class              #51            // java/lang/Enum\n   #17 = Utf8               X86\n   #18 = Utf8               Type\n   #19 = Utf8               InnerClasses\n   #20 = Utf8               Lorg/apache/commons/lang3/arch/Processor$Type;\n   #21 = Utf8               IA_64\n   #22 = Utf8               PPC\n   #23 = Utf8               UNKNOWN\n@@ -35,42 +35,38 @@\n   #25 = Utf8               [Lorg/apache/commons/lang3/arch/Processor$Type;\n   #26 = Utf8               values\n   #27 = Utf8               ()[Lorg/apache/commons/lang3/arch/Processor$Type;\n   #28 = Utf8               Code\n   #29 = Utf8               LineNumberTable\n   #30 = Utf8               valueOf\n   #31 = Utf8               (Ljava/lang/String;)Lorg/apache/commons/lang3/arch/Processor$Type;\n-  #32 = Utf8               LocalVariableTable\n-  #33 = Utf8               name\n-  #34 = Utf8               Ljava/lang/String;\n-  #35 = Utf8               <init>\n-  #36 = Utf8               (Ljava/lang/String;I)V\n-  #37 = Utf8               this\n-  #38 = Utf8               Signature\n-  #39 = Utf8               ()V\n-  #40 = Utf8               <clinit>\n-  #41 = Utf8               Ljava/lang/Enum<Lorg/apache/commons/lang3/arch/Processor$Type;>;\n-  #42 = Utf8               SourceFile\n-  #43 = Utf8               Processor.java\n-  #44 = NameAndType        #24:#25        // $VALUES:[Lorg/apache/commons/lang3/arch/Processor$Type;\n-  #45 = Class              #25            // \"[Lorg/apache/commons/lang3/arch/Processor$Type;\"\n-  #46 = NameAndType        #56:#57        // clone:()Ljava/lang/Object;\n-  #47 = Class              #58            // org/apache/commons/lang3/arch/Processor\n-  #48 = Utf8               org/apache/commons/lang3/arch/Processor$Type\n-  #49 = NameAndType        #30:#59        // valueOf:(Ljava/lang/Class;Ljava/lang/String;)Ljava/lang/Enum;\n-  #50 = NameAndType        #35:#36        // \"<init>\":(Ljava/lang/String;I)V\n-  #51 = NameAndType        #17:#20        // X86:Lorg/apache/commons/lang3/arch/Processor$Type;\n-  #52 = NameAndType        #21:#20        // IA_64:Lorg/apache/commons/lang3/arch/Processor$Type;\n-  #53 = NameAndType        #22:#20        // PPC:Lorg/apache/commons/lang3/arch/Processor$Type;\n-  #54 = NameAndType        #23:#20        // UNKNOWN:Lorg/apache/commons/lang3/arch/Processor$Type;\n-  #55 = Utf8               java/lang/Enum\n-  #56 = Utf8               clone\n-  #57 = Utf8               ()Ljava/lang/Object;\n-  #58 = Utf8               org/apache/commons/lang3/arch/Processor\n-  #59 = Utf8               (Ljava/lang/Class;Ljava/lang/String;)Ljava/lang/Enum;\n+  #32 = Utf8               <init>\n+  #33 = Utf8               (Ljava/lang/String;I)V\n+  #34 = Utf8               Signature\n+  #35 = Utf8               ()V\n+  #36 = Utf8               <clinit>\n+  #37 = Utf8               Ljava/lang/Enum<Lorg/apache/commons/lang3/arch/Processor$Type;>;\n+  #38 = Utf8               SourceFile\n+  #39 = Utf8               Processor.java\n+  #40 = NameAndType        #24:#25        // $VALUES:[Lorg/apache/commons/lang3/arch/Processor$Type;\n+  #41 = Class              #25            // \"[Lorg/apache/commons/lang3/arch/Processor$Type;\"\n+  #42 = NameAndType        #52:#53        // clone:()Ljava/lang/Object;\n+  #43 = Class              #54            // org/apache/commons/lang3/arch/Processor\n+  #44 = Utf8               org/apache/commons/lang3/arch/Processor$Type\n+  #45 = NameAndType        #30:#55        // valueOf:(Ljava/lang/Class;Ljava/lang/String;)Ljava/lang/Enum;\n+  #46 = NameAndType        #32:#33        // \"<init>\":(Ljava/lang/String;I)V\n+  #47 = NameAndType        #17:#20        // X86:Lorg/apache/commons/lang3/arch/Processor$Type;\n+  #48 = NameAndType        #21:#20        // IA_64:Lorg/apache/commons/lang3/arch/Processor$Type;\n+  #49 = NameAndType        #22:#20        // PPC:Lorg/apache/commons/lang3/arch/Processor$Type;\n+  #50 = NameAndType        #23:#20        // UNKNOWN:Lorg/apache/commons/lang3/arch/Processor$Type;\n+  #51 = Utf8               java/lang/Enum\n+  #52 = Utf8               clone\n+  #53 = Utf8               ()Ljava/lang/Object;\n+  #54 = Utf8               org/apache/commons/lang3/arch/Processor\n+  #55 = Utf8               (Ljava/lang/Class;Ljava/lang/String;)Ljava/lang/Enum;\n {\n   public static final org.apache.commons.lang3.arch.Processor$Type X86;\n     descriptor: Lorg/apache/commons/lang3/arch/Processor$Type;\n     flags: (0x4019) ACC_PUBLIC, ACC_STATIC, ACC_FINAL, ACC_ENUM\n \n   public static final org.apache.commons.lang3.arch.Processor$Type IA_64;\n     descriptor: Lorg/apache/commons/lang3/arch/Processor$Type;\n@@ -108,34 +104,28 @@\n          0: ldc           #4                  // class org/apache/commons/lang3/arch/Processor$Type\n          2: aload_0\n          3: invokestatic  #5                  // Method java/lang/Enum.valueOf:(Ljava/lang/Class;Ljava/lang/String;)Ljava/lang/Enum;\n          6: checkcast     #4                  // class org/apache/commons/lang3/arch/Processor$Type\n          9: areturn\n       LineNumberTable:\n         line 65: 0\n-      LocalVariableTable:\n-        Start  Length  Slot  Name   Signature\n-            0      10     0  name   Ljava/lang/String;\n \n   private org.apache.commons.lang3.arch.Processor$Type();\n     descriptor: (Ljava/lang/String;I)V\n     flags: (0x0002) ACC_PRIVATE\n     Code:\n       stack=3, locals=3, args_size=3\n          0: aload_0\n          1: aload_1\n          2: iload_2\n          3: invokespecial #6                  // Method java/lang/Enum.\"<init>\":(Ljava/lang/String;I)V\n          6: return\n       LineNumberTable:\n         line 65: 0\n-      LocalVariableTable:\n-        Start  Length  Slot  Name   Signature\n-            0       7     0  this   Lorg/apache/commons/lang3/arch/Processor$Type;\n-    Signature: #39                          // ()V\n+    Signature: #35                          // ()V\n \n   static {};\n     descriptor: ()V\n     flags: (0x0008) ACC_STATIC\n     Code:\n       stack=4, locals=0, args_size=0\n          0: new           #4                  // class org/apache/commons/lang3/arch/Processor$Type\n@@ -185,11 +175,11 @@\n       LineNumberTable:\n         line 70: 0\n         line 75: 13\n         line 80: 26\n         line 85: 39\n         line 65: 52\n }\n-Signature: #41                          // Ljava/lang/Enum<Lorg/apache/commons/lang3/arch/Processor$Type;>;\n+Signature: #37                          // Ljava/lang/Enum<Lorg/apache/commons/lang3/arch/Processor$Type;>;\n SourceFile: \"Processor.java\"\n InnerClasses:\n-  public static final #18= #4 of #47;     // Type=class org/apache/commons/lang3/arch/Processor$Type of class org/apache/commons/lang3/arch/Processor\n+  public static final #18= #4 of #43;     // Type=class org/apache/commons/lang3/arch/Processor$Type of class org/apache/commons/lang3/arch/Processor\n"}]}
