{"diffoscope-json-version": 1, "source1": "first/PasswordRequiredException.class", "source2": "second/PasswordRequiredException.class", "unified_diff": null, "details": [{"source1": "javap -verbose -constants -s -l -private {}", "source2": "javap -verbose -constants -s -l -private {}", "unified_diff": "@@ -1,81 +1,78 @@\n-  SHA-256 checksum a064ac2daa57dd2bde34c18a62b99498416b7d18641ad5e53de359f48e7c2538\n+  SHA-256 checksum 8ca26fba0f76f7fcab58f6edabedc05d542721aa5faf398ced5a48ee7ce5db79\n   Compiled from \"PasswordRequiredException.java\"\n public class org.apache.commons.compress.PasswordRequiredException extends java.io.IOException\n   minor version: 0\n   major version: 51\n   flags: (0x0021) ACC_PUBLIC, ACC_SUPER\n-  this_class: #8                          // org/apache/commons/compress/PasswordRequiredException\n-  super_class: #9                         // java/io/IOException\n+  this_class: #1                          // org/apache/commons/compress/PasswordRequiredException\n+  super_class: #3                         // java/io/IOException\n   interfaces: 0, fields: 1, methods: 1, attributes: 1\n Constant pool:\n-   #1 = Class              #26            // java/lang/StringBuilder\n-   #2 = Methodref          #1.#27         // java/lang/StringBuilder.\"<init>\":()V\n-   #3 = String             #28            // Cannot read encrypted content from\n-   #4 = Methodref          #1.#29         // java/lang/StringBuilder.append:(Ljava/lang/String;)Ljava/lang/StringBuilder;\n-   #5 = String             #30            //  without a password.\n-   #6 = Methodref          #1.#31         // java/lang/StringBuilder.toString:()Ljava/lang/String;\n-   #7 = Methodref          #9.#32         // java/io/IOException.\"<init>\":(Ljava/lang/String;)V\n-   #8 = Class              #33            // org/apache/commons/compress/PasswordRequiredException\n-   #9 = Class              #34            // java/io/IOException\n-  #10 = Utf8               serialVersionUID\n-  #11 = Utf8               J\n-  #12 = Utf8               ConstantValue\n-  #13 = Long               1391070005491684483l\n-  #15 = Utf8               <init>\n-  #16 = Utf8               (Ljava/lang/String;)V\n-  #17 = Utf8               Code\n-  #18 = Utf8               LineNumberTable\n-  #19 = Utf8               LocalVariableTable\n-  #20 = Utf8               this\n-  #21 = Utf8               Lorg/apache/commons/compress/PasswordRequiredException;\n-  #22 = Utf8               name\n-  #23 = Utf8               Ljava/lang/String;\n-  #24 = Utf8               SourceFile\n-  #25 = Utf8               PasswordRequiredException.java\n-  #26 = Utf8               java/lang/StringBuilder\n-  #27 = NameAndType        #15:#35        // \"<init>\":()V\n-  #28 = Utf8               Cannot read encrypted content from\n-  #29 = NameAndType        #36:#37        // append:(Ljava/lang/String;)Ljava/lang/StringBuilder;\n-  #30 = Utf8                without a password.\n-  #31 = NameAndType        #38:#39        // toString:()Ljava/lang/String;\n-  #32 = NameAndType        #15:#16        // \"<init>\":(Ljava/lang/String;)V\n-  #33 = Utf8               org/apache/commons/compress/PasswordRequiredException\n-  #34 = Utf8               java/io/IOException\n-  #35 = Utf8               ()V\n-  #36 = Utf8               append\n-  #37 = Utf8               (Ljava/lang/String;)Ljava/lang/StringBuilder;\n-  #38 = Utf8               toString\n-  #39 = Utf8               ()Ljava/lang/String;\n+   #1 = Class              #2             // org/apache/commons/compress/PasswordRequiredException\n+   #2 = Utf8               org/apache/commons/compress/PasswordRequiredException\n+   #3 = Class              #4             // java/io/IOException\n+   #4 = Utf8               java/io/IOException\n+   #5 = Utf8               serialVersionUID\n+   #6 = Utf8               J\n+   #7 = Utf8               ConstantValue\n+   #8 = Long               1391070005491684483l\n+  #10 = Utf8               <init>\n+  #11 = Utf8               (Ljava/lang/String;)V\n+  #12 = Utf8               Code\n+  #13 = Class              #14            // java/lang/StringBuilder\n+  #14 = Utf8               java/lang/StringBuilder\n+  #15 = String             #16            // Cannot read encrypted content from\n+  #16 = Utf8               Cannot read encrypted content from\n+  #17 = Methodref          #13.#18        // java/lang/StringBuilder.\"<init>\":(Ljava/lang/String;)V\n+  #18 = NameAndType        #10:#11        // \"<init>\":(Ljava/lang/String;)V\n+  #19 = Methodref          #13.#20        // java/lang/StringBuilder.append:(Ljava/lang/String;)Ljava/lang/StringBuilder;\n+  #20 = NameAndType        #21:#22        // append:(Ljava/lang/String;)Ljava/lang/StringBuilder;\n+  #21 = Utf8               append\n+  #22 = Utf8               (Ljava/lang/String;)Ljava/lang/StringBuilder;\n+  #23 = String             #24            //  without a password.\n+  #24 = Utf8                without a password.\n+  #25 = Methodref          #13.#26        // java/lang/StringBuilder.toString:()Ljava/lang/String;\n+  #26 = NameAndType        #27:#28        // toString:()Ljava/lang/String;\n+  #27 = Utf8               toString\n+  #28 = Utf8               ()Ljava/lang/String;\n+  #29 = Methodref          #3.#18         // java/io/IOException.\"<init>\":(Ljava/lang/String;)V\n+  #30 = Utf8               LineNumberTable\n+  #31 = Utf8               LocalVariableTable\n+  #32 = Utf8               this\n+  #33 = Utf8               Lorg/apache/commons/compress/PasswordRequiredException;\n+  #34 = Utf8               name\n+  #35 = Utf8               Ljava/lang/String;\n+  #36 = Utf8               SourceFile\n+  #37 = Utf8               PasswordRequiredException.java\n {\n   private static final long serialVersionUID = 1391070005491684483l;\n     descriptor: J\n     flags: (0x001a) ACC_PRIVATE, ACC_STATIC, ACC_FINAL\n     ConstantValue: long 1391070005491684483l\n \n   public org.apache.commons.compress.PasswordRequiredException(java.lang.String);\n     descriptor: (Ljava/lang/String;)V\n     flags: (0x0001) ACC_PUBLIC\n     Code:\n-      stack=3, locals=2, args_size=2\n+      stack=4, locals=2, args_size=2\n          0: aload_0\n-         1: new           #1                  // class java/lang/StringBuilder\n+         1: new           #13                 // class java/lang/StringBuilder\n          4: dup\n-         5: invokespecial #2                  // Method java/lang/StringBuilder.\"<init>\":()V\n-         8: ldc           #3                  // String Cannot read encrypted content from\n-        10: invokevirtual #4                  // Method java/lang/StringBuilder.append:(Ljava/lang/String;)Ljava/lang/StringBuilder;\n-        13: aload_1\n-        14: invokevirtual #4                  // Method java/lang/StringBuilder.append:(Ljava/lang/String;)Ljava/lang/StringBuilder;\n-        17: ldc           #5                  // String  without a password.\n-        19: invokevirtual #4                  // Method java/lang/StringBuilder.append:(Ljava/lang/String;)Ljava/lang/StringBuilder;\n-        22: invokevirtual #6                  // Method java/lang/StringBuilder.toString:()Ljava/lang/String;\n-        25: invokespecial #7                  // Method java/io/IOException.\"<init>\":(Ljava/lang/String;)V\n-        28: return\n+         5: ldc           #15                 // String Cannot read encrypted content from\n+         7: invokespecial #17                 // Method java/lang/StringBuilder.\"<init>\":(Ljava/lang/String;)V\n+        10: aload_1\n+        11: invokevirtual #19                 // Method java/lang/StringBuilder.append:(Ljava/lang/String;)Ljava/lang/StringBuilder;\n+        14: ldc           #23                 // String  without a password.\n+        16: invokevirtual #19                 // Method java/lang/StringBuilder.append:(Ljava/lang/String;)Ljava/lang/StringBuilder;\n+        19: invokevirtual #25                 // Method java/lang/StringBuilder.toString:()Ljava/lang/String;\n+        22: invokespecial #29                 // Method java/io/IOException.\"<init>\":(Ljava/lang/String;)V\n+        25: return\n       LineNumberTable:\n         line 38: 0\n-        line 39: 28\n+        line 39: 25\n       LocalVariableTable:\n         Start  Length  Slot  Name   Signature\n-            0      29     0  this   Lorg/apache/commons/compress/PasswordRequiredException;\n-            0      29     1  name   Ljava/lang/String;\n+            0      26     0  this   Lorg/apache/commons/compress/PasswordRequiredException;\n+            0      26     1  name   Ljava/lang/String;\n }\n SourceFile: \"PasswordRequiredException.java\"\n"}]}
